<?xml version="1.0"?>
<Numbering><TypeNumber Concrete="1" ShortTypeName="CONCNmdEntt" TypeNo="128"/><TypeNumber Concrete="1" ShortTypeName="TpMngr" TypeNo="129"><AttributeNumber Complexity="1" FieldNo="10031" ShortFieldName="allTps" Target="120"/><AttributeNumber Complexity="0" FieldNo="10032" ShortFieldName="This" Target="129"/></TypeNumber><TypeNumber Concrete="1" ShortTypeName="CmmndExctr" TypeNo="-130"><AttributeNumber Complexity="1" FieldNo="10033" ShortFieldName="commands" Target="111"/></TypeNumber><TypeNumber Concrete="1" ShortTypeName="OrMtTp" TypeNo="117"/><TypeNumber Concrete="1" ShortTypeName="AspctMngr" TypeNo="131"><AttributeNumber Complexity="1" FieldNo="10034" ShortFieldName="aspcts" Target="119"/><AttributeNumber Complexity="0" FieldNo="10035" ShortFieldName="This" Target="131"/></TypeNumber><TypeNumber Concrete="1" ShortTypeName="MtAspct" TypeNo="119"><AttributeNumber Complexity="1" FieldNo="10036" ShortFieldName="types" Target="122"/></TypeNumber><TypeNumber Concrete="1" ShortTypeName="ErrorDisplay" TypeNo="-109"><AttributeNumber Complexity="0" FieldNo="10012" ShortFieldName="message" Target="2"/><AttributeNumber Complexity="0" FieldNo="10013" ShortFieldName="This" Target="-109"/></TypeNumber><TypeNumber Concrete="1" ShortTypeName="Srvr" TypeNo="-125"><AttributeNumber Complexity="0" FieldNo="10037" ShortFieldName="aspectManager" Target="131"/><AttributeNumber Complexity="0" FieldNo="10038" ShortFieldName="typeManager" Target="129"/><AttributeNumber Complexity="0" FieldNo="10021" ShortFieldName="This" Target="-125"/><AttributeNumber Complexity="1" FieldNo="10022" ShortFieldName="errors" Target="-109"/><AttributeNumber Complexity="0" FieldNo="10023" ShortFieldName="password" Target="2"/><AttributeNumber Complexity="0" FieldNo="10024" ShortFieldName="user" Target="2"/><AttributeNumber Complexity="0" FieldNo="10025" ShortFieldName="hackCount" Target="1"/><AttributeNumber Complexity="0" FieldNo="10026" ShortFieldName="hackDelay" Target="5"/></TypeNumber><TypeNumber Concrete="0" ShortTypeName="NmdEntt" TypeNo="124"><AttributeNumber Complexity="0" FieldNo="10019" ShortFieldName="nm" Target="2"/><AttributeNumber Complexity="0" FieldNo="10020" ShortFieldName="This" Target="124"/></TypeNumber><TypeNumber Concrete="1" ShortTypeName="MtAssctn" TypeNo="126"><AttributeNumber Complexity="0" FieldNo="10051" ShortFieldName="src" Target="120"/><AttributeNumber Complexity="0" FieldNo="10052" ShortFieldName="trgt" Target="120"/><AttributeNumber Complexity="1" FieldNo="10029" ShortFieldName="hrrchs" Target="121"/></TypeNumber><TypeNumber Concrete="1" ShortTypeName="CrtAspctCMD" TypeNo="132"><AttributeNumber Complexity="0" FieldNo="10039" ShortFieldName="nm" Target="2"/><AttributeNumber Complexity="0" FieldNo="10040" ShortFieldName="invoker" Target="110"/><AttributeNumber Complexity="0" FieldNo="10041" ShortFieldName="cReceiver" Target="131"/><AttributeNumber Complexity="0" FieldNo="10042" ShortFieldName="myCmmnDt" Target="134"/></TypeNumber><TypeNumber Concrete="1" ShortTypeName="CmmndCrdntr" TypeNo="-133"><AttributeNumber Complexity="1" FieldNo="10043" ShortFieldName="exctr" Target="-130"/></TypeNumber><TypeNumber Concrete="1" ShortTypeName="CmmnDt" TypeNo="134"><AttributeNumber Complexity="0" FieldNo="10044" ShortFieldName="crtdt" Target="3"/><AttributeNumber Complexity="0" FieldNo="10045" ShortFieldName="cmmtdt" Target="3"/></TypeNumber><TypeNumber Concrete="1" ShortTypeName="AndMtTp" TypeNo="118"/><TypeNumber Concrete="0" ShortTypeName="AbstrctMtTp" TypeNo="120"><AttributeNumber Complexity="0" FieldNo="10014" ShortFieldName="This" Target="120"/></TypeNumber><TypeNumber Concrete="1" ShortTypeName="MtHrrch" TypeNo="121"/><TypeNumber Concrete="0" ShortTypeName="CmpsdMtTp" TypeNo="123"><AttributeNumber Complexity="1" FieldNo="10018" ShortFieldName="cmpnnts" Target="120"/><AttributeNumber Complexity="0" FieldNo="10053" ShortFieldName="disjunctiveNormalform" Target="117"/></TypeNumber><TypeNumber Concrete="1" ShortTypeName="MtTp" TypeNo="122"><AttributeNumber Complexity="1" FieldNo="10015" ShortFieldName="sbtps" Target="122"/><AttributeNumber Complexity="0" FieldNo="10016" ShortFieldName="mAspct" Target="119"/><AttributeNumber Complexity="0" FieldNo="10030" ShortFieldName="myCONCNmdEntt" Target="124"/></TypeNumber><TypeNumber Concrete="1" ShortTypeName="CrtTpCMD" TypeNo="135"><AttributeNumber Complexity="0" FieldNo="10046" ShortFieldName="nm" Target="2"/><AttributeNumber Complexity="0" FieldNo="10047" ShortFieldName="aspct" Target="119"/><AttributeNumber Complexity="0" FieldNo="10048" ShortFieldName="invoker" Target="110"/><AttributeNumber Complexity="0" FieldNo="10049" ShortFieldName="cReceiver" Target="129"/><AttributeNumber Complexity="0" FieldNo="10050" ShortFieldName="myCmmnDt" Target="134"/></TypeNumber><TypeNumber Concrete="0" ShortTypeName="Invoker" TypeNo="110"/><TypeNumber Concrete="0" ShortTypeName="CMD" TypeNo="111"/><TypeNumber Concrete="0" ShortTypeName="Remote" TypeNo="127"/><TypeNumber Concrete="0" ShortTypeName="TpMngrCMD" TypeNo="136"/><TypeNumber Concrete="0" ShortTypeName="AspctMngrCMD" TypeNo="137"/><TypeNumber Concrete="0" ShortTypeName="Dcrts" TypeNo="112"/><TypeNumber Concrete="0" ShortTypeName="Anything" TypeNo="113"/><TypeNumber Concrete="1" ShortTypeName="CycleException" TypeNo="-114"/><TypeNumber Concrete="0" ShortTypeName="UserException" TypeNo="-115"/><TypeNumber Concrete="1" ShortTypeName="DoubleDefinitionException" TypeNo="-138"/><TypeNumber Concrete="1" ShortTypeName="RestrictionException" TypeNo="-116"/></Numbering>